onlinestoremanager/__init__.py
onlinestoremanager/__main__.py
onlinestoremanager/order_management.py
onlinestoremanager/user_management.py
onlinestoremanager-0.1.2.dist-info/METADATA
onlinestoremanager-0.1.2.dist-info/WHEEL
onlinestoremanager-0.1.2.dist-info/entry_points.txt
onlinestoremanager-0.1.2.dist-info/top_level.txt
onlinestoremanager-0.1.2.dist-info/RECORD
