Metadata-Version: 2.1
Name: onlinestoremanager
Version: 0.1.2
Summary: Исполняемый пакет для управления пользователями и заказами в онлайн-магазине
Author-email: Dusya <Lev.khrobostov@mail.ru>
License: MIT
Requires-Python: >=3.8
Provides-Extra: dev
Requires-Dist: pytest >=6.2.1 ; extra == 'dev'
Requires-Dist: flake8 >=3.8.4 ; extra == 'dev'
